yodi/Yodi.py
yodi/__init__.py
yodis-0.0.7.dist-info/LICENSE
yodis-0.0.7.dist-info/METADATA
yodis-0.0.7.dist-info/WHEEL
yodis-0.0.7.dist-info/top_level.txt
yodis-0.0.7.dist-info/RECORD
