Metadata-Version: 2.1
Name: yodis
Version: 0.0.7
License-File: LICENSE
Requires-Dist: pathlib
Requires-Dist: tensorflow
Requires-Dist: matplotlib
Requires-Dist: numpy
Requires-Dist: seaborn
Requires-Dist: IPython
Requires-Dist: gradio
